setup.py
crate_riot/__init__.py
crate_riot.egg-info/PKG-INFO
crate_riot.egg-info/SOURCES.txt
crate_riot.egg-info/dependency_links.txt
crate_riot.egg-info/not-zip-safe
crate_riot.egg-info/top_level.txt