Metadata-Version: 1.0
Name: crate-riot
Version: 0.1
Summary: Getting data from crate server
Home-page: https://bitbucket.org/research_iot/tutorial_docker_crate_python
Author: Jingyi Guo
Author-email: plips4847@gmail.com
License: Phil
Platform: UNKNOWN
